fastapi_matrix_admin/__init__.py
fastapi_matrix_admin/audit/__init__.py
fastapi_matrix_admin/audit/models.py
fastapi_matrix_admin/auth/__init__.py
fastapi_matrix_admin/auth/models.py
fastapi_matrix_admin/auth/service.py
fastapi_matrix_admin/auth/utils.py
fastapi_matrix_admin/core/__init__.py
fastapi_matrix_admin/core/admin.py
fastapi_matrix_admin/core/crud.py
fastapi_matrix_admin/core/database.py
fastapi_matrix_admin/core/discovery.py
fastapi_matrix_admin/core/export.py
fastapi_matrix_admin/core/integrator.py
fastapi_matrix_admin/core/rate_limiter.py
fastapi_matrix_admin/core/registry.py
fastapi_matrix_admin/core/router.py
fastapi_matrix_admin/core/security.py
fastapi_matrix_admin/statics/alpine.min.js
fastapi_matrix_admin/statics/htmx.min.js
fastapi_matrix_admin/templates/components/buttons.html
fastapi_matrix_admin/templates/components/cards.html
fastapi_matrix_admin/templates/components/inputs.html
fastapi_matrix_admin/templates/components/table.html
fastapi_matrix_admin/templates/fragments/form_fields.html
fastapi_matrix_admin/templates/layouts/base.html
fastapi_matrix_admin/templates/pages/edit.html
fastapi_matrix_admin/templates/pages/index.html
fastapi_matrix_admin/templates/pages/list.html
fastapi_matrix_admin/templates/pages/login.html
fastapi_matrix_admin-1.0.3.dist-info/METADATA
fastapi_matrix_admin-1.0.3.dist-info/WHEEL
fastapi_matrix_admin-1.0.3.dist-info/licenses/LICENSE.md
fastapi_matrix_admin-1.0.3.dist-info/RECORD
