Metadata-Version: 2.4
Name: fastapi-matrix-admin
Version: 1.0.3
Summary: ⚡ FastAPI Admin Panel with Stunning Matrix UI Theme - Terminal-Style, Cyberpunk Aesthetics
Project-URL: Homepage, https://github.com/rasinmuhammed/fastapi-matrix-admin
Project-URL: Documentation, https://github.com/rasinmuhammed/fastapi-matrix-admin#readme
Project-URL: Repository, https://github.com/rasinmuhammed/fastapi-matrix-admin
Project-URL: Bug Tracker, https://github.com/rasinmuhammed/fastapi-matrix-admin/issues
Project-URL: Changelog, https://github.com/rasinmuhammed/fastapi-matrix-admin/blob/main/CHANGELOG.md
Author: fastapi-matrix-admin contributors
License: MIT
License-File: LICENSE.md
Keywords: admin,cyberpunk,fastapi,htmx,matrix,pydantic,terminal
Classifier: Development Status :: 4 - Beta
Classifier: Framework :: FastAPI
Classifier: Intended Audience :: Developers
Classifier: License :: OSI Approved :: MIT License
Classifier: Programming Language :: Python :: 3
Classifier: Programming Language :: Python :: 3.10
Classifier: Programming Language :: Python :: 3.11
Classifier: Programming Language :: Python :: 3.12
Classifier: Topic :: Internet :: WWW/HTTP :: HTTP Servers
Classifier: Typing :: Typed
Requires-Python: >=3.10
Requires-Dist: fastapi>=0.100.0
Requires-Dist: itsdangerous>=2.1.0
Requires-Dist: jinja2>=3.1.0
Requires-Dist: passlib[argon2]>=1.7.4
Requires-Dist: psutil>=5.9.0
Requires-Dist: pydantic>=2.0
Requires-Dist: pydantic[email]>=2.0
Requires-Dist: python-multipart>=0.0.6
Requires-Dist: sqlalchemy[asyncio]>=2.0
Provides-Extra: dev
Requires-Dist: aiosqlite>=0.19; extra == 'dev'
Requires-Dist: bandit>=1.7; extra == 'dev'
Requires-Dist: black>=23.0; extra == 'dev'
Requires-Dist: httpx>=0.24; extra == 'dev'
Requires-Dist: pytest-asyncio>=0.21; extra == 'dev'
Requires-Dist: pytest-cov>=4.0; extra == 'dev'
Requires-Dist: pytest>=7.0; extra == 'dev'
Requires-Dist: ruff>=0.1.0; extra == 'dev'
Requires-Dist: uvicorn>=0.23; extra == 'dev'
